{"dependencies":[{"name":"graphql","loc":{"line":19,"column":23}},{"name":"graphql/language/kinds","loc":{"line":21,"column":21}},{"name":"graphql-language-service-utils","loc":{"line":23,"column":43}}],"generated":{"js":"'use strict';\n\nObject.defineProperty(exports, \"__esModule\", {\n  value: true\n});\n\nvar _extends = Object.assign || function (target) { for (var i = 1; i < arguments.length; i++) { var source = arguments[i]; for (var key in source) { if (Object.prototype.hasOwnProperty.call(source, key)) { target[key] = source[key]; } } } return target; }; /**\n                                                                                                                                                                                                                                                                   *  Copyright (c) Facebook, Inc.\n                                                                                                                                                                                                                                                                   *  All rights reserved.\n                                                                                                                                                                                                                                                                   *\n                                                                                                                                                                                                                                                                   *  This source code is licensed under the license found in the\n                                                                                                                                                                                                                                                                   *  LICENSE file in the root directory of this source tree.\n                                                                                                                                                                                                                                                                   *\n                                                                                                                                                                                                                                                                   *  \n                                                                                                                                                                                                                                                                   */\n\nexports.getOutline = getOutline;\n\nvar _graphql = require('graphql');\n\nvar _kinds = require('graphql/language/kinds');\n\nvar _graphqlLanguageServiceUtils = require('graphql-language-service-utils');\n\nvar OUTLINEABLE_KINDS = {\n  Field: true,\n  OperationDefinition: true,\n  Document: true,\n  SelectionSet: true,\n  Name: true,\n  FragmentDefinition: true,\n  FragmentSpread: true,\n  InlineFragment: true\n};\n\nfunction getOutline(queryText) {\n  var ast = void 0;\n  try {\n    ast = (0, _graphql.parse)(queryText);\n  } catch (error) {\n    return null;\n  }\n\n  var visitorFns = outlineTreeConverter(queryText);\n  var outlineTrees = (0, _graphql.visit)(ast, {\n    leave: function leave(node) {\n      if (OUTLINEABLE_KINDS[node.kind] && visitorFns[node.kind]) {\n        return visitorFns[node.kind](node);\n      }\n      return null;\n    }\n  });\n  return { outlineTrees: outlineTrees };\n}\n\nfunction outlineTreeConverter(docText) {\n  var meta = function meta(node) {\n    return {\n      representativeName: node.name,\n      startPosition: (0, _graphqlLanguageServiceUtils.offsetToPosition)(docText, node.loc.start),\n      endPosition: (0, _graphqlLanguageServiceUtils.offsetToPosition)(docText, node.loc.end),\n      children: node.selectionSet || []\n    };\n  };\n  return {\n    Field: function Field(node) {\n      var tokenizedText = node.alias ? [buildToken('plain', node.alias), buildToken('plain', ': ')] : [];\n      tokenizedText.push(buildToken('plain', node.name));\n      return _extends({ tokenizedText: tokenizedText }, meta(node));\n    },\n    OperationDefinition: function OperationDefinition(node) {\n      return _extends({\n        tokenizedText: [buildToken('keyword', node.operation), buildToken('whitespace', ' '), buildToken('class-name', node.name)]\n      }, meta(node));\n    },\n    Document: function Document(node) {\n      return node.definitions;\n    },\n    SelectionSet: function SelectionSet(node) {\n      return concatMap(node.selections, function (child) {\n        return child.kind === _kinds.INLINE_FRAGMENT ? child.selectionSet : child;\n      });\n    },\n    Name: function Name(node) {\n      return node.value;\n    },\n    FragmentDefinition: function FragmentDefinition(node) {\n      return _extends({\n        tokenizedText: [buildToken('keyword', 'fragment'), buildToken('whitespace', ' '), buildToken('class-name', node.name)]\n      }, meta(node));\n    },\n    FragmentSpread: function FragmentSpread(node) {\n      return _extends({\n        tokenizedText: [buildToken('plain', '...'), buildToken('class-name', node.name)]\n      }, meta(node));\n    },\n    InlineFragment: function InlineFragment(node) {\n      return node.selectionSet;\n    }\n  };\n}\n\nfunction buildToken(kind, value) {\n  return { kind: kind, value: value };\n}\n\nfunction concatMap(arr, fn) {\n  var res = [];\n  for (var i = 0; i < arr.length; i++) {\n    var x = fn(arr[i], i);\n    if (Array.isArray(x)) {\n      res.push.apply(res, x);\n    } else {\n      res.push(x);\n    }\n  }\n  return res;\n}"},"hash":"65b9a7a927e7c88b900e852e7ab51f35"}