{"dependencies":[{"name":"react/lib/ReactComponentTreeHook","loc":{"line":11,"column":37}},{"name":"fbjs/lib/warning","loc":{"line":13,"column":22}}],"generated":{"js":"\"use strict\";function e(e,n){null!=n&&(\"input\"!==n.type&&\"textarea\"!==n.type&&\"select\"!==n.type||null==n.props||null!==n.props.value||t||(t=!0))}var n=require(\"react/lib/ReactComponentTreeHook\"),o=require(\"fbjs/lib/warning\"),t=!1,r={onBeforeMountComponent:function(n,o){e(n,o)},onBeforeUpdateComponent:function(n,o){e(n,o)}};module.exports=r;"},"hash":"05dbcd4832e8740cb35ded47d129ed72"}