{"dependencies":[{"name":"react","loc":{"line":9,"column":21}},{"name":"prop-types","loc":{"line":13,"column":25}},{"name":"./TypeLink","loc":{"line":17,"column":24}},{"name":"./MarkdownContent","loc":{"line":21,"column":31}}],"generated":{"js":"'use strict';\n\nObject.defineProperty(exports, \"__esModule\", {\n  value: true\n});\n\nvar _createClass = function () { function defineProperties(target, props) { for (var i = 0; i < props.length; i++) { var descriptor = props[i]; descriptor.enumerable = descriptor.enumerable || false; descriptor.configurable = true; if (\"value\" in descriptor) descriptor.writable = true; Object.defineProperty(target, descriptor.key, descriptor); } } return function (Constructor, protoProps, staticProps) { if (protoProps) defineProperties(Constructor.prototype, protoProps); if (staticProps) defineProperties(Constructor, staticProps); return Constructor; }; }();\n\nvar _react = require('react');\n\nvar _react2 = _interopRequireDefault(_react);\n\nvar _propTypes = require('prop-types');\n\nvar _propTypes2 = _interopRequireDefault(_propTypes);\n\nvar _TypeLink = require('./TypeLink');\n\nvar _TypeLink2 = _interopRequireDefault(_TypeLink);\n\nvar _MarkdownContent = require('./MarkdownContent');\n\nvar _MarkdownContent2 = _interopRequireDefault(_MarkdownContent);\n\nfunction _interopRequireDefault(obj) { return obj && obj.__esModule ? obj : { default: obj }; }\n\nfunction _classCallCheck(instance, Constructor) { if (!(instance instanceof Constructor)) { throw new TypeError(\"Cannot call a class as a function\"); } }\n\nfunction _possibleConstructorReturn(self, call) { if (!self) { throw new ReferenceError(\"this hasn't been initialised - super() hasn't been called\"); } return call && (typeof call === \"object\" || typeof call === \"function\") ? call : self; }\n\nfunction _inherits(subClass, superClass) { if (typeof superClass !== \"function\" && superClass !== null) { throw new TypeError(\"Super expression must either be null or a function, not \" + typeof superClass); } subClass.prototype = Object.create(superClass && superClass.prototype, { constructor: { value: subClass, enumerable: false, writable: true, configurable: true } }); if (superClass) Object.setPrototypeOf ? Object.setPrototypeOf(subClass, superClass) : subClass.__proto__ = superClass; } /**\n                                                                                                                                                                                                                                                                                                                                                                                                                                                                                                                *  Copyright (c) Facebook, Inc.\n                                                                                                                                                                                                                                                                                                                                                                                                                                                                                                                *  All rights reserved.\n                                                                                                                                                                                                                                                                                                                                                                                                                                                                                                                *\n                                                                                                                                                                                                                                                                                                                                                                                                                                                                                                                *  This source code is licensed under the license found in the\n                                                                                                                                                                                                                                                                                                                                                                                                                                                                                                                *  LICENSE file in the root directory of this source tree.\n                                                                                                                                                                                                                                                                                                                                                                                                                                                                                                                */\n\n// Render the top level Schema\nvar SchemaDoc = function (_React$Component) {\n  _inherits(SchemaDoc, _React$Component);\n\n  function SchemaDoc() {\n    _classCallCheck(this, SchemaDoc);\n\n    return _possibleConstructorReturn(this, (SchemaDoc.__proto__ || Object.getPrototypeOf(SchemaDoc)).apply(this, arguments));\n  }\n\n  _createClass(SchemaDoc, [{\n    key: 'shouldComponentUpdate',\n    value: function shouldComponentUpdate(nextProps) {\n      return this.props.schema !== nextProps.schema;\n    }\n  }, {\n    key: 'render',\n    value: function render() {\n      var schema = this.props.schema;\n      var queryType = schema.getQueryType();\n      var mutationType = schema.getMutationType && schema.getMutationType();\n      var subscriptionType = schema.getSubscriptionType && schema.getSubscriptionType();\n\n      return _react2.default.createElement(\n        'div',\n        null,\n        _react2.default.createElement(_MarkdownContent2.default, {\n          className: 'doc-type-description',\n          markdown: 'A GraphQL schema provides a root type for each kind of operation.'\n        }),\n        _react2.default.createElement(\n          'div',\n          { className: 'doc-category' },\n          _react2.default.createElement(\n            'div',\n            { className: 'doc-category-title' },\n            'root types'\n          ),\n          _react2.default.createElement(\n            'div',\n            { className: 'doc-category-item' },\n            _react2.default.createElement(\n              'span',\n              { className: 'keyword' },\n              'query'\n            ),\n            ': ',\n            _react2.default.createElement(_TypeLink2.default, { type: queryType, onClick: this.props.onClickType })\n          ),\n          mutationType && _react2.default.createElement(\n            'div',\n            { className: 'doc-category-item' },\n            _react2.default.createElement(\n              'span',\n              { className: 'keyword' },\n              'mutation'\n            ),\n            ': ',\n            _react2.default.createElement(_TypeLink2.default, { type: mutationType, onClick: this.props.onClickType })\n          ),\n          subscriptionType && _react2.default.createElement(\n            'div',\n            { className: 'doc-category-item' },\n            _react2.default.createElement(\n              'span',\n              { className: 'keyword' },\n              'subscription'\n            ),\n            ': ',\n            _react2.default.createElement(_TypeLink2.default, {\n              type: subscriptionType,\n              onClick: this.props.onClickType\n            })\n          )\n        )\n      );\n    }\n  }]);\n\n  return SchemaDoc;\n}(_react2.default.Component);\n\nSchemaDoc.propTypes = {\n  schema: _propTypes2.default.object,\n  onClickType: _propTypes2.default.func\n};\nexports.default = SchemaDoc;"},"hash":"2ab278861a12d7ac3ad465a8519b29a0"}